cryptpickle/__init__.py
cryptpickle-0.9.dist-info/LICENSE.txt
cryptpickle-0.9.dist-info/WHEEL
cryptpickle-0.9.dist-info/METADATA
cryptpickle-0.9.dist-info/RECORD
