Metadata-Version: 2.1
Name: cryptpickle
Version: 0.9
Summary: Encrypted python object serialization
Author-email: Privtools <privacy-dad@protonmail.com>
Requires-Python: >=3.7
Classifier: Programming Language :: Python :: 3.7
Classifier: Programming Language :: Python :: 3.8
Classifier: Programming Language :: Python :: 3.9
Classifier: Programming Language :: Python :: 3.10
Classifier: Development Status :: 4 - Beta
Classifier: License :: OSI Approved :: European Union Public Licence 1.2 (EUPL 1.2)
Classifier: Operating System :: OS Independent
Classifier: Topic :: Scientific/Engineering
Classifier: Topic :: Security
Requires-Dist: pyzipper
Project-URL: Home, https://github.com/privtools/CryptPickle
